mokt/__init__.py
mokt/cli_runner.py
mokt/test.py
mokt/test_data.py
mokt/test_environment.py
mokt-0.9.dist-info/METADATA
mokt-0.9.dist-info/RECORD
mokt-0.9.dist-info/WHEEL
mokt-0.9.dist-info/top_level.txt
