Metadata-Version: 2.1
Name: mokt
Version: 0.9
Summary: A simple framework for automated testing of OpenCL kernels
Home-page: https://github.com/band-of-four/master-of-kernel-testing
Author: Band of Four
License: CC0 1.0
Platform: UNKNOWN
Classifier: Programming Language :: Python :: 3
Classifier: Intended Audience :: Developers
Classifier: Topic :: Software Development :: Testing
Classifier: License :: CC0 1.0 Universal (CC0 1.0) Public Domain Dedication
Requires-Dist: tensorflow (>=1.5)
Requires-Dist: pyopencl
Requires-Dist: termcolor
